LICENSE
MANIFEST.in
README.md
pyproject.toml
setup.cfg
setup.py
versioneer.py
src/sigmadsp/__init__.py
src/sigmadsp/_version.py
src/sigmadsp.egg-info/PKG-INFO
src/sigmadsp.egg-info/SOURCES.txt
src/sigmadsp.egg-info/dependency_links.txt
src/sigmadsp.egg-info/entry_points.txt
src/sigmadsp.egg-info/requires.txt
src/sigmadsp.egg-info/top_level.txt
src/sigmadsp/application/__init__.py
src/sigmadsp/application/backend.py
src/sigmadsp/application/frontend.py
src/sigmadsp/communication/__init__.py
src/sigmadsp/communication/sigma_tcp_server.py
src/sigmadsp/generated/__init__.py
src/sigmadsp/generated/backend_service/__init__.py
src/sigmadsp/generated/backend_service/control_pb2.py
src/sigmadsp/generated/backend_service/control_pb2_grpc.py
src/sigmadsp/hardware/__init__.py
src/sigmadsp/hardware/adau14xx.py
src/sigmadsp/hardware/dsp.py
src/sigmadsp/hardware/spi.py
src/sigmadsp/helper/__init__.py
src/sigmadsp/helper/conversion.py
src/sigmadsp/helper/parser.py
src/sigmadsp/helper/settings.py