Metadata-Version: 2.1
Name: sigmadsp
Version: 1.5.0
Summary: A package for controlling Analog Devices Sigma DSP chipsets.
Home-page: https://github.com/elagil/sigmadsp
Author: Adrian Figueroa
Author-email: elagil@takanome.de
License: UNKNOWN
Project-URL: Bug Tracker, https://github.com/elagil/sigmadsp/issues
Platform: UNKNOWN
Classifier: Programming Language :: Python :: 3
Classifier: License :: OSI Approved :: GNU General Public License v3 or later (GPLv3+)
Classifier: Operating System :: OS Independent
Requires-Python: >=3.6
License-File: LICENSE
